whai/__init__.py
whai/__main__.py
whai/constants.py
whai/logging_setup.py
whai/cli/__init__.py
whai/cli/flags.py
whai/cli/main.py
whai/cli/role.py
whai/configuration/__init__.py
whai/configuration/config_wizard.py
whai/configuration/roles.py
whai/configuration/user_config.py
whai/context/__init__.py
whai/context/capture.py
whai/context/history.py
whai/context/normalization.py
whai/context/session_reader.py
whai/context/tmux.py
whai/core/__init__.py
whai/core/executor.py
whai/core/session_logger.py
whai/defaults/system_prompt.txt
whai/defaults/roles/default.md
whai/defaults/roles/new.md
whai/doc/CHANGELOG.md
whai/doc/DEV.md
whai/doc/TODO.md
whai/doc/release_notes.py
whai/interaction/__init__.py
whai/interaction/approval.py
whai/interaction/execution.py
whai/interaction/tool_calls.py
whai/llm/__init__.py
whai/llm/prompts.py
whai/llm/provider.py
whai/llm/ssl_cache.py
whai/llm/streaming.py
whai/llm/token_utils.py
whai/shell/__init__.py
whai/shell/session.py
whai/ui/__init__.py
whai/ui/formatting.py
whai/ui/output.py
whai/utils/__init__.py
whai/utils/perf_logger.py
whai-0.8.2.dist-info/METADATA
whai-0.8.2.dist-info/WHEEL
whai-0.8.2.dist-info/entry_points.txt
whai-0.8.2.dist-info/licenses/LICENSE
whai-0.8.2.dist-info/RECORD
