Metadata-Version: 2.4
Name: whai
Version: 0.8.2
Summary: A lightweight, Python-based CLI tool that integrates LLMs directly into your terminal
Author: whai Contributors
License: MIT
License-File: LICENSE
Requires-Python: >=3.10
Requires-Dist: litellm>=1.0.0
Requires-Dist: pyyaml>=6.0
Requires-Dist: rich>=13.7.0
Requires-Dist: tomli-w>=1.0.0
Requires-Dist: tomli>=2.0.0; python_version < '3.11'
Requires-Dist: typer>=0.9.0
